odoo/addons/stock_archive_constraint/README.rst
odoo/addons/stock_archive_constraint/__init__.py
odoo/addons/stock_archive_constraint/__manifest__.py
odoo/addons/stock_archive_constraint/i18n/es.po
odoo/addons/stock_archive_constraint/i18n/it.po
odoo/addons/stock_archive_constraint/i18n/stock_archive_constraint.pot
odoo/addons/stock_archive_constraint/models/__init__.py
odoo/addons/stock_archive_constraint/models/product_product.py
odoo/addons/stock_archive_constraint/models/stock_location.py
odoo/addons/stock_archive_constraint/readme/CONTRIBUTORS.md
odoo/addons/stock_archive_constraint/readme/DESCRIPTION.md
odoo/addons/stock_archive_constraint/readme/USAGE.md
odoo/addons/stock_archive_constraint/static/description/icon.png
odoo/addons/stock_archive_constraint/static/description/index.html
odoo/addons/stock_archive_constraint/tests/__init__.py
odoo/addons/stock_archive_constraint/tests/test_location_archive_constraint.py
odoo_addon_stock_archive_constraint-18.0.1.0.0.7.dist-info/METADATA
odoo_addon_stock_archive_constraint-18.0.1.0.0.7.dist-info/WHEEL
odoo_addon_stock_archive_constraint-18.0.1.0.0.7.dist-info/top_level.txt
odoo_addon_stock_archive_constraint-18.0.1.0.0.7.dist-info/RECORD
